frdm/__init__.py
frdm/account.py
frdm/alert.py
frdm/api_call.py
frdm/device.py
frdm/entity.py
frdm/helpers.py
frdm/user.py
frdm/zone.py
frdm-1.0.4.dist-info/METADATA
frdm-1.0.4.dist-info/WHEEL
frdm-1.0.4.dist-info/top_level.txt
frdm-1.0.4.dist-info/RECORD
